<?xml version="1.0" encoding="UTF-8"?>  
<beans xmlns="http://www.springframework.org/schema/beans" 
	xmlns:xsi="http://www.w3.org/2001/XMLSchema-instance" 
	xmlns:context="http://www.springframework.org/schema/context" 
	xmlns:tx="http://www.springframework.org/schema/tx" 
	xmlns:p="http://www.springframework.org/schema/p" 
	xmlns:aop="http://www.springframework.org/schema/aop" 
	xsi:schemaLocation="http://www.springframework.org/schema/beans  http://www.springframework.org/schema/beans/spring-beans-3.0.xsd  http://www.springframework.org/schema/context  http://www.springframework.org/schema/context/spring-context-3.0.xsd  http://www.springframework.org/schema/tx  http://www.springframework.org/schema/tx/spring-tx-3.0.xsd  http://www.springframework.org/schema/aop  http://www.springframework.org/schema/aop/spring-aop-3.0.xsd">
 
	<!-- 资源权限自动补齐拦截器  -->
	<bean id="ResourcePermissionInterceptor" class="com.boubei.tss.um.permission.ResourcePermissionInterceptor"/>
	<bean class="org.springframework.aop.framework.autoproxy.BeanNameAutoProxyCreator">
		<property name="beanNames"> <value>*DAO, *Dao</value> </property>
		<property name="interceptorNames">
			<list>
				<value>ResourcePermissionInterceptor</value>
			</list>
		</property>
	</bean>
	
	<!-- 对资源进行权限过滤或检查的拦截器 -->
	<bean id="PermissionCheckInterceptor" class="com.boubei.tss.um.permission.filter.PermissionCheckInterceptor"/>
	<bean class="org.springframework.aop.framework.autoproxy.BeanNameAutoProxyCreator">
		<property name="beanNames"> <value> *Service, *DAO, *Dao </value> </property>
		<property name="interceptorNames">
			<list>
				<value>PermissionCheckInterceptor</value>
			</list>
		</property>
	</bean>
 
</beans>